<?xml version="1.0" encoding="UTF-8" ?>
<!DOCTYPE tiles-definitions PUBLIC
       "-//Apache Software Foundation//DTD Tiles Configuration 2.0//EN"
       "http://tiles.apache.org/dtds/tiles-config_2_0.dtd">
<tiles-definitions>

	<definition name="baseLayout" template="/BaseLayout.jsp"  >
		<put-attribute name="title" value="Welcome to Login Page" />
		<put-attribute name="header" value="/Header.jsp" />
        <put-attribute name="body" value="/Bodypage.jsp" />
		<put-attribute name="footer" value="/Footer.jsp" />
	</definition>
	
 
 <definition name="Home" extends="baseLayout" >
		<put-attribute name="title" value="Welcome to Login Page" />
		<put-attribute name="body" value="/HomePage.jsp" />
		</definition>
 
 <definition name="CustInfo" extends="baseLayout" >
		<put-attribute name="title" value="Welcome to CustInfo Page" />
		<put-attribute name="body" value="/CustInfoPage.jsp" />
</definition>


<definition name="AddOn" extends="baseLayout" >
		<put-attribute name="title" value="Welcome to AddOn Page" />
		<put-attribute name="body" value="/AddOn.jsp" />
</definition>

 	 <definition name="VehicleSelection" extends="baseLayout" >
		<put-attribute name="title" value="Welcome to Vehicleselect Page" />
		<put-attribute name="body" value="/VehicleSelection.jsp" />
</definition>

 	<definition name="Login" extends="baseLayout" >
		<put-attribute name="title" value="Welcome to Login Page" />
		<put-attribute name="body" value="/LoginPage.jsp" />
		</definition>
		
		
		 <definition name="ConfirmBooking" extends="baseLayout" >
		<put-attribute name="title" value="Welcome to ConfirmBoomking Page" />
		<put-attribute name="body" value="/ConfirmBooking.jsp" />
		</definition>
		
		<definition name="MemReg" extends="baseLayout" >
		<put-attribute name="title" value="Welcome to Login Page" />
		<put-attribute name="body" value="/MemRegPage.jsp" />
		</definition>
		
		
		 <definition name="AboutUs" extends="baseLayout" >
		<put-attribute name="title" value="Welcome to AboutUs Page" />
		<put-attribute name="body" value="/AboutUsPage.jsp" />
		</definition>
		
 		<definition name="Careers" extends="baseLayout" >
		<put-attribute name="title" value="Welcome to Careers Page" />
		<put-attribute name="body" value="/CareersPage.jsp" />
		</definition>
		
		<definition name="ContactUs" extends="baseLayout" >
		<put-attribute name="title" value="Welcome to ContactUs Page" />
		<put-attribute name="body" value="/ContactUsPage.jsp" />
		</definition>
		
			<definition name="Location" extends="baseLayout" >
		<put-attribute name="title" value="Welcome to Location Page" />
		<put-attribute name="body" value="/LocationSelectionPage.jsp" />
		</definition>
		
			<definition name="Affiliatedhotels" extends="baseLayout" >
		<put-attribute name="title" value="Welcome to Affiliatedhotels Page" />
		<put-attribute name="body" value="/AffiliatedhotelsPage.jsp" />
		</definition>
		
			
		
			<definition name="Bill" extends="baseLayout" >
		<put-attribute name="title" value="Welcome to Bill Page" />
		<put-attribute name="body" value="/BillPage.jsp" />
		</definition>
		
			
		
		
</tiles-definitions>